LICENSE
MANIFEST.in
README.rst
VERSION
requirements.txt
setup.cfg
setup.py
docs/conf.py
docs/index.rst
docs/installation.rst
docs/settings.rst
ycsettings/__init__.py
ycsettings/settings.py
ycsettings.egg-info/PKG-INFO
ycsettings.egg-info/SOURCES.txt
ycsettings.egg-info/dependency_links.txt
ycsettings.egg-info/requires.txt
ycsettings.egg-info/top_level.txt
ycsettings.egg-info/zip-safe