Metadata-Version: 1.1
Name: ycsettings
Version: 0.1.5
Summary: A utility module for handling app settings.
Home-page: https://github.com/skylander86/ycsettings
Author: Yanchuan Sim
Author-email: yanchuan@outlook.com
License: Apache Software License 2.0
Keywords: ycsettings
Platform: UNKNOWN
Classifier: Development Status :: 4 - Beta
Classifier: Intended Audience :: Developers
Classifier: License :: OSI Approved :: Apache Software License
Classifier: Programming Language :: Python :: 2.7
Classifier: Programming Language :: Python :: 3
